[{"siteId":"smbrnd","device":"PC","menuId":1,"parntsMenuId":0,"menuNm":"홈","menuTy":null,"linkTarget":null,"linkUrl":null,"linkMenuId":0,"linkBoardId":null,"linkParam":null,"popupParam":null,"themeId":null,"layout":null,"showAt":"Y","useAt":null,"level":0,"permGrp":"","permLvl":0},{"siteId":"smbrnd","device":"PC","menuId":2,"parntsMenuId":1,"menuNm":"시스템소개","menuTy":"LINK_IN","linkTarget":"_SELF","linkUrl":"/smbrnd/sub.do?m=6","linkMenuId":2,"linkBoardId":"","linkParam":null,"popupParam":null,"themeId":"smbrnd","layout":"sub_layout.jsp","showAt":"Y","useAt":null,"level":0,"permGrp":"","permLvl":0},{"siteId":"smbrnd","device":"PC","menuId":6,"parntsMenuId":2,"menuNm":"SMBRND소개","menuTy":"HTML","linkTarget":"_SELF","linkUrl":null,"linkMenuId":2,"linkBoardId":"","linkParam":null,"popupParam":null,"themeId":"smbrnd","layout":"sub_layout.jsp","showAt":"Y","useAt":null,"level":0,"permGrp":"","permLvl":0},{"siteId":"smbrnd","device":"PC","menuId":12,"parntsMenuId":2,"menuNm":"SMBRND인사말","menuTy":"HTML","linkTarget":"_SELF","linkUrl":null,"linkMenuId":2,"linkBoardId":"","linkParam":null,"popupParam":null,"themeId":"smbrnd","layout":"sub_layout.jsp","showAt":"Y","useAt":null,"level":0,"permGrp":"","permLvl":0},{"siteId":"smbrnd","device":"PC","menuId":3,"parntsMenuId":1,"menuNm":"사업공고","menuTy":"LINK_IN","linkTarget":"_SELF","linkUrl":"/smbrnd/sub.do?m=7","linkMenuId":2,"linkBoardId":"","linkParam":null,"popupParam":null,"themeId":"smbrnd","layout":"sub_layout.jsp","showAt":"Y","useAt":null,"level":0,"permGrp":"","permLvl":0},{"siteId":"smbrnd","device":"PC","menuId":7,"parntsMenuId":3,"menuNm":"사업현황","menuTy":"HTML","linkTarget":"_SELF","linkUrl":null,"linkMenuId":2,"linkBoardId":"","linkParam":null,"popupParam":null,"themeId":"smbrnd","layout":"sub_layout.jsp","showAt":"Y","useAt":null,"level":0,"permGrp":"","permLvl":0},{"siteId":"smbrnd","device":"PC","menuId":8,"parntsMenuId":3,"menuNm":"지원계획","menuTy":"JSP","linkTarget":"_SELF","linkUrl":null,"linkMenuId":2,"linkBoardId":"","linkParam":null,"popupParam":null,"themeId":"smbrnd","layout":"sub_layout.jsp","showAt":"Y","useAt":null,"level":0,"permGrp":"","permLvl":0},{"siteId":"smbrnd","device":"PC","menuId":20,"parntsMenuId":3,"menuNm":"맞춤사업검색","menuTy":"HTML","linkTarget":"_SELF","linkUrl":null,"linkMenuId":2,"linkBoardId":"","linkParam":null,"popupParam":null,"themeId":"smbrnd","layout":"sub_layout.jsp","showAt":"Y","useAt":null,"level":0,"permGrp":"","permLvl":0},{"siteId":"smbrnd","device":"PC","menuId":4,"parntsMenuId":1,"menuNm":"정보","menuTy":"LINK_IN","linkTarget":"_SELF","linkUrl":"/smbrnd/sub.do?m=9","linkMenuId":2,"linkBoardId":"","linkParam":null,"popupParam":null,"themeId":"smbrnd","layout":"sub_layout.jsp","showAt":"Y","useAt":null,"level":0,"permGrp":"","permLvl":0},{"siteId":"smbrnd","device":"PC","menuId":9,"parntsMenuId":4,"menuNm":"전문가정보","menuTy":"JSP","linkTarget":"_SELF","linkUrl":null,"linkMenuId":2,"linkBoardId":"","linkParam":null,"popupParam":null,"themeId":"smbrnd","layout":"sub_layout.jsp","showAt":"Y","useAt":null,"level":0,"permGrp":"","permLvl":0},{"siteId":"smbrnd","device":"PC","menuId":13,"parntsMenuId":4,"menuNm":"전문가등록","menuTy":"JSP","linkTarget":"_SELF","linkUrl":null,"linkMenuId":2,"linkBoardId":"","linkParam":null,"popupParam":null,"themeId":"smbrnd","layout":"sub_layout.jsp","showAt":"Y","useAt":null,"level":0,"permGrp":"","permLvl":0},{"siteId":"smbrnd","device":"PC","menuId":5,"parntsMenuId":1,"menuNm":"중소기업통계","menuTy":"LINK_IN","linkTarget":"_SELF","linkUrl":"/smbrnd/sub.do?m=10","linkMenuId":2,"linkBoardId":"","linkParam":null,"popupParam":null,"themeId":"smbrnd","layout":"sub_layout.jsp","showAt":"Y","useAt":null,"level":0,"permGrp":"","permLvl":0},{"siteId":"smbrnd","device":"PC","menuId":10,"parntsMenuId":5,"menuNm":"R&D과제현황","menuTy":"HTML","linkTarget":"_SELF","linkUrl":null,"linkMenuId":2,"linkBoardId":"","linkParam":null,"popupParam":null,"themeId":"smbrnd","layout":"sub_layout.jsp","showAt":"Y","useAt":null,"level":0,"permGrp":"","permLvl":0},{"siteId":"smbrnd","device":"PC","menuId":11,"parntsMenuId":5,"menuNm":"연구조직","menuTy":"HTML","linkTarget":"_SELF","linkUrl":null,"linkMenuId":2,"linkBoardId":"","linkParam":null,"popupParam":null,"themeId":"smbrnd","layout":"sub_layout.jsp","showAt":"Y","useAt":null,"level":0,"permGrp":"","permLvl":0},{"siteId":"smbrnd","device":"PC","menuId":15,"parntsMenuId":14,"menuNm":"SITEMAP","menuTy":"JSP","linkTarget":"_SELF","linkUrl":null,"linkMenuId":2,"linkBoardId":"","linkParam":null,"popupParam":null,"themeId":"smbrnd","layout":"sub_layout.jsp","showAt":"N","useAt":null,"level":0,"permGrp":"","permLvl":0},{"siteId":"smbrnd","device":"PC","menuId":14,"parntsMenuId":1,"menuNm":"교육정보","menuTy":"LINK_IN","linkTarget":"_SELF","linkUrl":"/smbrnd/sub.do?m=14","linkMenuId":2,"linkBoardId":"","linkParam":null,"popupParam":null,"themeId":"smbrnd","layout":"sub_layout.jsp","showAt":"Y","useAt":null,"level":0,"permGrp":"","permLvl":0},{"siteId":"smbrnd","device":"PC","menuId":16,"parntsMenuId":14,"menuNm":"찾아오시는길","menuTy":"JSP","linkTarget":"_SELF","linkUrl":null,"linkMenuId":2,"linkBoardId":"","linkParam":null,"popupParam":null,"themeId":"smbrnd","layout":"sub_layout.jsp","showAt":"N","useAt":null,"level":0,"permGrp":"","permLvl":0},{"siteId":"smbrnd","device":"PC","menuId":17,"parntsMenuId":14,"menuNm":"이메일무단수집거부","menuTy":"JSP","linkTarget":"_SELF","linkUrl":null,"linkMenuId":2,"linkBoardId":"","linkParam":null,"popupParam":null,"themeId":"smbrnd","layout":"sub_layout.jsp","showAt":"N","useAt":null,"level":0,"permGrp":"","permLvl":0},{"siteId":"smbrnd","device":"PC","menuId":18,"parntsMenuId":14,"menuNm":"개인정보처리방침","menuTy":"JSP","linkTarget":"_SELF","linkUrl":null,"linkMenuId":2,"linkBoardId":"","linkParam":null,"popupParam":null,"themeId":"smbrnd","layout":"sub_layout.jsp","showAt":"N","useAt":null,"level":0,"permGrp":"","permLvl":0},{"siteId":"smbrnd","device":"PC","menuId":19,"parntsMenuId":14,"menuNm":"저작권정책","menuTy":"HTML","linkTarget":"_SELF","linkUrl":null,"linkMenuId":2,"linkBoardId":"","linkParam":null,"popupParam":null,"themeId":"smbrnd","layout":"sub_layout.jsp","showAt":"N","useAt":null,"level":0,"permGrp":"","permLvl":0}]